[
    {
        "iteration": 0,
        "model_name": "Dummy random classifier",
        "mean_squared_error": 0,
        "accuracy_metrics": {
            "train": {
                "current": 6.428571428571428,
                "next": null,
                "remaining": null,
                "remaining_count": NaN,
                "is_last": null,
                "object_general_class": null
            },
            "val": {
                "current": 25.0,
                "next": null,
                "remaining": null,
                "remaining_count": NaN,
                "is_last": null,
                "object_general_class": null
            },
            "test": {
                "current": 7.5,
                "next": null,
                "remaining": null,
                "remaining_count": NaN,
                "is_last": null,
                "object_general_class": null
            },
            "combined": {
                "current": 8.16326530612245,
                "next": null,
                "remaining": null,
                "remaining_count": NaN,
                "is_last": null,
                "object_general_class": null
            }
        }
    },
    {
        "iteration": 0,
        "model_name": "CLIP",
        "mean_squared_error": 0,
        "accuracy_metrics": {
            "train": {
                "current": 87.14285714285714,
                "next": null,
                "remaining": null,
                "remaining_count": NaN,
                "is_last": null,
                "object_general_class": null
            },
            "val": {
                "current": 18.75,
                "next": null,
                "remaining": null,
                "remaining_count": NaN,
                "is_last": null,
                "object_general_class": null
            },
            "test": {
                "current": 12.5,
                "next": null,
                "remaining": null,
                "remaining_count": NaN,
                "is_last": null,
                "object_general_class": null
            },
            "combined": {
                "current": 66.3265306122449,
                "next": null,
                "remaining": null,
                "remaining_count": NaN,
                "is_last": null,
                "object_general_class": null
            }
        }
    }
]