{
  "version": "5.2.0.post4",
  "flags": {},
  "module": "cnc",
  "camera": "basler",
  "shapes": [
    {
      "label": "firealarm_back",
      "points": [
        [
          468.0,
          377.0
        ],
        [
          467.0,
          378.0
        ],
        [
          463.0,
          378.0
        ],
        [
          462.0,
          379.0
        ],
        [
          459.0,
          379.0
        ],
        [
          458.0,
          380.0
        ],
        [
          456.0,
          380.0
        ],
        [
          455.0,
          381.0
        ],
        [
          453.0,
          381.0
        ],
        [
          452.0,
          382.0
        ],
        [
          450.0,
          382.0
        ],
        [
          449.0,
          383.0
        ],
        [
          448.0,
          383.0
        ],
        [
          447.0,
          384.0
        ],
        [
          446.0,
          384.0
        ],
        [
          445.0,
          385.0
        ],
        [
          443.0,
          385.0
        ],
        [
          442.0,
          386.0
        ],
        [
          441.0,
          386.0
        ],
        [
          440.0,
          387.0
        ],
        [
          438.0,
          387.0
        ],
        [
          437.0,
          388.0
        ],
        [
          436.0,
          388.0
        ],
        [
          435.0,
          389.0
        ],
        [
          434.0,
          389.0
        ],
        [
          433.0,
          390.0
        ],
        [
          432.0,
          390.0
        ],
        [
          430.0,
          392.0
        ],
        [
          429.0,
          392.0
        ],
        [
          427.0,
          394.0
        ],
        [
          426.0,
          394.0
        ],
        [
          425.0,
          395.0
        ],
        [
          424.0,
          395.0
        ],
        [
          423.0,
          396.0
        ],
        [
          422.0,
          396.0
        ],
        [
          419.0,
          399.0
        ],
        [
          418.0,
          399.0
        ],
        [
          416.0,
          401.0
        ],
        [
          415.0,
          401.0
        ],
        [
          403.0,
          413.0
        ],
        [
          403.0,
          414.0
        ],
        [
          398.0,
          419.0
        ],
        [
          398.0,
          420.0
        ],
        [
          395.0,
          423.0
        ],
        [
          395.0,
          424.0
        ],
        [
          394.0,
          425.0
        ],
        [
          394.0,
          426.0
        ],
        [
          391.0,
          429.0
        ],
        [
          391.0,
          430.0
        ],
        [
          389.0,
          432.0
        ],
        [
          389.0,
          433.0
        ],
        [
          388.0,
          434.0
        ],
        [
          388.0,
          435.0
        ],
        [
          387.0,
          436.0
        ],
        [
          387.0,
          437.0
        ],
        [
          386.0,
          438.0
        ],
        [
          386.0,
          439.0
        ],
        [
          385.0,
          440.0
        ],
        [
          385.0,
          441.0
        ],
        [
          384.0,
          442.0
        ],
        [
          384.0,
          443.0
        ],
        [
          383.0,
          444.0
        ],
        [
          383.0,
          446.0
        ],
        [
          382.0,
          447.0
        ],
        [
          382.0,
          450.0
        ],
        [
          381.0,
          451.0
        ],
        [
          381.0,
          452.0
        ],
        [
          380.0,
          453.0
        ],
        [
          380.0,
          456.0
        ],
        [
          379.0,
          457.0
        ],
        [
          379.0,
          460.0
        ],
        [
          378.0,
          461.0
        ],
        [
          378.0,
          465.0
        ],
        [
          377.0,
          466.0
        ],
        [
          377.0,
          469.0
        ],
        [
          376.0,
          470.0
        ],
        [
          376.0,
          476.0
        ],
        [
          375.0,
          477.0
        ],
        [
          375.0,
          504.0
        ],
        [
          376.0,
          505.0
        ],
        [
          376.0,
          509.0
        ],
        [
          377.0,
          510.0
        ],
        [
          377.0,
          514.0
        ],
        [
          378.0,
          515.0
        ],
        [
          378.0,
          518.0
        ],
        [
          379.0,
          519.0
        ],
        [
          379.0,
          520.0
        ],
        [
          380.0,
          521.0
        ],
        [
          380.0,
          523.0
        ],
        [
          381.0,
          524.0
        ],
        [
          381.0,
          527.0
        ],
        [
          382.0,
          528.0
        ],
        [
          382.0,
          530.0
        ],
        [
          383.0,
          531.0
        ],
        [
          383.0,
          532.0
        ],
        [
          384.0,
          533.0
        ],
        [
          384.0,
          535.0
        ],
        [
          385.0,
          536.0
        ],
        [
          385.0,
          538.0
        ],
        [
          386.0,
          539.0
        ],
        [
          386.0,
          540.0
        ],
        [
          387.0,
          541.0
        ],
        [
          387.0,
          542.0
        ],
        [
          389.0,
          544.0
        ],
        [
          389.0,
          545.0
        ],
        [
          390.0,
          546.0
        ],
        [
          390.0,
          547.0
        ],
        [
          392.0,
          549.0
        ],
        [
          392.0,
          550.0
        ],
        [
          393.0,
          551.0
        ],
        [
          393.0,
          552.0
        ],
        [
          395.0,
          554.0
        ],
        [
          395.0,
          555.0
        ],
        [
          397.0,
          557.0
        ],
        [
          397.0,
          558.0
        ],
        [
          400.0,
          561.0
        ],
        [
          400.0,
          562.0
        ],
        [
          404.0,
          566.0
        ],
        [
          404.0,
          567.0
        ],
        [
          414.0,
          577.0
        ],
        [
          415.0,
          577.0
        ],
        [
          418.0,
          580.0
        ],
        [
          419.0,
          580.0
        ],
        [
          422.0,
          583.0
        ],
        [
          423.0,
          583.0
        ],
        [
          425.0,
          585.0
        ],
        [
          426.0,
          585.0
        ],
        [
          428.0,
          587.0
        ],
        [
          429.0,
          587.0
        ],
        [
          432.0,
          590.0
        ],
        [
          433.0,
          590.0
        ],
        [
          435.0,
          592.0
        ],
        [
          436.0,
          592.0
        ],
        [
          438.0,
          594.0
        ],
        [
          439.0,
          594.0
        ],
        [
          441.0,
          596.0
        ],
        [
          442.0,
          596.0
        ],
        [
          443.0,
          597.0
        ],
        [
          444.0,
          597.0
        ],
        [
          445.0,
          598.0
        ],
        [
          446.0,
          598.0
        ],
        [
          447.0,
          599.0
        ],
        [
          448.0,
          599.0
        ],
        [
          449.0,
          600.0
        ],
        [
          450.0,
          600.0
        ],
        [
          451.0,
          601.0
        ],
        [
          453.0,
          601.0
        ],
        [
          454.0,
          602.0
        ],
        [
          456.0,
          602.0
        ],
        [
          457.0,
          603.0
        ],
        [
          459.0,
          603.0
        ],
        [
          460.0,
          604.0
        ],
        [
          462.0,
          604.0
        ],
        [
          463.0,
          605.0
        ],
        [
          465.0,
          605.0
        ],
        [
          466.0,
          606.0
        ],
        [
          469.0,
          606.0
        ],
        [
          470.0,
          607.0
        ],
        [
          503.0,
          607.0
        ],
        [
          504.0,
          606.0
        ],
        [
          511.0,
          606.0
        ],
        [
          512.0,
          605.0
        ],
        [
          517.0,
          605.0
        ],
        [
          518.0,
          604.0
        ],
        [
          519.0,
          604.0
        ],
        [
          520.0,
          603.0
        ],
        [
          522.0,
          603.0
        ],
        [
          523.0,
          602.0
        ],
        [
          525.0,
          602.0
        ],
        [
          526.0,
          601.0
        ],
        [
          528.0,
          601.0
        ],
        [
          529.0,
          600.0
        ],
        [
          530.0,
          600.0
        ],
        [
          531.0,
          599.0
        ],
        [
          532.0,
          599.0
        ],
        [
          533.0,
          598.0
        ],
        [
          534.0,
          598.0
        ],
        [
          535.0,
          597.0
        ],
        [
          536.0,
          597.0
        ],
        [
          537.0,
          596.0
        ],
        [
          538.0,
          596.0
        ],
        [
          539.0,
          595.0
        ],
        [
          540.0,
          595.0
        ],
        [
          541.0,
          594.0
        ],
        [
          542.0,
          594.0
        ],
        [
          543.0,
          593.0
        ],
        [
          544.0,
          593.0
        ],
        [
          545.0,
          592.0
        ],
        [
          546.0,
          592.0
        ],
        [
          548.0,
          590.0
        ],
        [
          549.0,
          590.0
        ],
        [
          550.0,
          589.0
        ],
        [
          551.0,
          589.0
        ],
        [
          553.0,
          587.0
        ],
        [
          554.0,
          587.0
        ],
        [
          556.0,
          585.0
        ],
        [
          557.0,
          585.0
        ],
        [
          572.0,
          570.0
        ],
        [
          572.0,
          569.0
        ],
        [
          578.0,
          563.0
        ],
        [
          578.0,
          562.0
        ],
        [
          580.0,
          560.0
        ],
        [
          580.0,
          559.0
        ],
        [
          581.0,
          558.0
        ],
        [
          581.0,
          557.0
        ],
        [
          583.0,
          555.0
        ],
        [
          583.0,
          554.0
        ],
        [
          585.0,
          552.0
        ],
        [
          585.0,
          551.0
        ],
        [
          586.0,
          550.0
        ],
        [
          586.0,
          549.0
        ],
        [
          587.0,
          548.0
        ],
        [
          587.0,
          547.0
        ],
        [
          588.0,
          546.0
        ],
        [
          588.0,
          545.0
        ],
        [
          589.0,
          544.0
        ],
        [
          589.0,
          543.0
        ],
        [
          591.0,
          541.0
        ],
        [
          591.0,
          540.0
        ],
        [
          592.0,
          539.0
        ],
        [
          592.0,
          538.0
        ],
        [
          593.0,
          537.0
        ],
        [
          593.0,
          536.0
        ],
        [
          594.0,
          535.0
        ],
        [
          594.0,
          533.0
        ],
        [
          595.0,
          532.0
        ],
        [
          595.0,
          531.0
        ],
        [
          596.0,
          530.0
        ],
        [
          596.0,
          528.0
        ],
        [
          597.0,
          527.0
        ],
        [
          597.0,
          524.0
        ],
        [
          598.0,
          523.0
        ],
        [
          598.0,
          520.0
        ],
        [
          599.0,
          519.0
        ],
        [
          599.0,
          516.0
        ],
        [
          600.0,
          515.0
        ],
        [
          600.0,
          510.0
        ],
        [
          601.0,
          509.0
        ],
        [
          601.0,
          502.0
        ],
        [
          602.0,
          501.0
        ],
        [
          602.0,
          483.0
        ],
        [
          601.0,
          482.0
        ],
        [
          601.0,
          474.0
        ],
        [
          600.0,
          473.0
        ],
        [
          600.0,
          465.0
        ],
        [
          599.0,
          464.0
        ],
        [
          599.0,
          458.0
        ],
        [
          598.0,
          457.0
        ],
        [
          598.0,
          456.0
        ],
        [
          597.0,
          455.0
        ],
        [
          597.0,
          454.0
        ],
        [
          596.0,
          453.0
        ],
        [
          596.0,
          452.0
        ],
        [
          595.0,
          451.0
        ],
        [
          595.0,
          450.0
        ],
        [
          594.0,
          449.0
        ],
        [
          594.0,
          447.0
        ],
        [
          593.0,
          446.0
        ],
        [
          593.0,
          445.0
        ],
        [
          592.0,
          444.0
        ],
        [
          592.0,
          443.0
        ],
        [
          591.0,
          442.0
        ],
        [
          591.0,
          440.0
        ],
        [
          590.0,
          439.0
        ],
        [
          590.0,
          438.0
        ],
        [
          589.0,
          437.0
        ],
        [
          589.0,
          436.0
        ],
        [
          588.0,
          435.0
        ],
        [
          588.0,
          434.0
        ],
        [
          587.0,
          433.0
        ],
        [
          587.0,
          432.0
        ],
        [
          586.0,
          431.0
        ],
        [
          586.0,
          430.0
        ],
        [
          584.0,
          428.0
        ],
        [
          584.0,
          427.0
        ],
        [
          583.0,
          426.0
        ],
        [
          583.0,
          425.0
        ],
        [
          582.0,
          424.0
        ],
        [
          582.0,
          423.0
        ],
        [
          576.0,
          417.0
        ],
        [
          576.0,
          416.0
        ],
        [
          568.0,
          408.0
        ],
        [
          567.0,
          408.0
        ],
        [
          565.0,
          406.0
        ],
        [
          565.0,
          405.0
        ],
        [
          563.0,
          403.0
        ],
        [
          562.0,
          403.0
        ],
        [
          557.0,
          398.0
        ],
        [
          556.0,
          398.0
        ],
        [
          554.0,
          396.0
        ],
        [
          553.0,
          396.0
        ],
        [
          551.0,
          394.0
        ],
        [
          550.0,
          394.0
        ],
        [
          548.0,
          392.0
        ],
        [
          547.0,
          392.0
        ],
        [
          546.0,
          391.0
        ],
        [
          545.0,
          391.0
        ],
        [
          544.0,
          390.0
        ],
        [
          543.0,
          390.0
        ],
        [
          541.0,
          388.0
        ],
        [
          539.0,
          388.0
        ],
        [
          538.0,
          387.0
        ],
        [
          537.0,
          387.0
        ],
        [
          536.0,
          386.0
        ],
        [
          534.0,
          386.0
        ],
        [
          533.0,
          385.0
        ],
        [
          531.0,
          385.0
        ],
        [
          530.0,
          384.0
        ],
        [
          529.0,
          384.0
        ],
        [
          528.0,
          383.0
        ],
        [
          527.0,
          383.0
        ],
        [
          526.0,
          382.0
        ],
        [
          524.0,
          382.0
        ],
        [
          523.0,
          381.0
        ],
        [
          520.0,
          381.0
        ],
        [
          519.0,
          380.0
        ],
        [
          517.0,
          380.0
        ],
        [
          516.0,
          379.0
        ],
        [
          513.0,
          379.0
        ],
        [
          512.0,
          378.0
        ],
        [
          507.0,
          378.0
        ],
        [
          506.0,
          377.0
        ],
        [
          501.0,
          377.0
        ],
        [
          500.0,
          376.0
        ],
        [
          478.0,
          376.0
        ],
        [
          477.0,
          377.0
        ]
      ],
      "group_id": null,
      "description": "",
      "shape_type": "polygon",
      "flags": {}
    },
    {
      "label": "pcb",
      "points": [
        [
          426.0,
          406.0
        ],
        [
          424.0,
          408.0
        ],
        [
          424.0,
          409.0
        ],
        [
          423.0,
          410.0
        ],
        [
          423.0,
          411.0
        ],
        [
          422.0,
          412.0
        ],
        [
          422.0,
          415.0
        ],
        [
          421.0,
          416.0
        ],
        [
          421.0,
          417.0
        ],
        [
          420.0,
          418.0
        ],
        [
          420.0,
          419.0
        ],
        [
          419.0,
          420.0
        ],
        [
          419.0,
          421.0
        ],
        [
          418.0,
          422.0
        ],
        [
          418.0,
          423.0
        ],
        [
          417.0,
          424.0
        ],
        [
          417.0,
          425.0
        ],
        [
          410.0,
          432.0
        ],
        [
          410.0,
          433.0
        ],
        [
          409.0,
          434.0
        ],
        [
          409.0,
          436.0
        ],
        [
          408.0,
          437.0
        ],
        [
          408.0,
          438.0
        ],
        [
          407.0,
          439.0
        ],
        [
          407.0,
          440.0
        ],
        [
          406.0,
          441.0
        ],
        [
          406.0,
          442.0
        ],
        [
          404.0,
          444.0
        ],
        [
          404.0,
          445.0
        ],
        [
          403.0,
          446.0
        ],
        [
          403.0,
          447.0
        ],
        [
          400.0,
          450.0
        ],
        [
          400.0,
          451.0
        ],
        [
          396.0,
          455.0
        ],
        [
          395.0,
          455.0
        ],
        [
          395.0,
          456.0
        ],
        [
          393.0,
          458.0
        ],
        [
          392.0,
          458.0
        ],
        [
          391.0,
          459.0
        ],
        [
          390.0,
          459.0
        ],
        [
          389.0,
          460.0
        ],
        [
          388.0,
          460.0
        ],
        [
          388.0,
          461.0
        ],
        [
          387.0,
          462.0
        ],
        [
          387.0,
          466.0
        ],
        [
          386.0,
          467.0
        ],
        [
          386.0,
          468.0
        ],
        [
          385.0,
          469.0
        ],
        [
          385.0,
          470.0
        ],
        [
          384.0,
          471.0
        ],
        [
          384.0,
          479.0
        ],
        [
          385.0,
          480.0
        ],
        [
          388.0,
          480.0
        ],
        [
          389.0,
          481.0
        ],
        [
          391.0,
          481.0
        ],
        [
          392.0,
          482.0
        ],
        [
          394.0,
          482.0
        ],
        [
          396.0,
          484.0
        ],
        [
          397.0,
          484.0
        ],
        [
          398.0,
          485.0
        ],
        [
          399.0,
          485.0
        ],
        [
          400.0,
          486.0
        ],
        [
          401.0,
          486.0
        ],
        [
          402.0,
          487.0
        ],
        [
          403.0,
          487.0
        ],
        [
          406.0,
          490.0
        ],
        [
          407.0,
          490.0
        ],
        [
          409.0,
          492.0
        ],
        [
          410.0,
          492.0
        ],
        [
          411.0,
          493.0
        ],
        [
          412.0,
          493.0
        ],
        [
          414.0,
          495.0
        ],
        [
          415.0,
          495.0
        ],
        [
          416.0,
          496.0
        ],
        [
          417.0,
          496.0
        ],
        [
          419.0,
          498.0
        ],
        [
          420.0,
          498.0
        ],
        [
          422.0,
          500.0
        ],
        [
          423.0,
          500.0
        ],
        [
          425.0,
          502.0
        ],
        [
          426.0,
          502.0
        ],
        [
          428.0,
          504.0
        ],
        [
          429.0,
          504.0
        ],
        [
          433.0,
          508.0
        ],
        [
          434.0,
          508.0
        ],
        [
          436.0,
          510.0
        ],
        [
          437.0,
          510.0
        ],
        [
          439.0,
          512.0
        ],
        [
          440.0,
          512.0
        ],
        [
          442.0,
          514.0
        ],
        [
          443.0,
          514.0
        ],
        [
          444.0,
          515.0
        ],
        [
          445.0,
          515.0
        ],
        [
          446.0,
          516.0
        ],
        [
          447.0,
          516.0
        ],
        [
          450.0,
          519.0
        ],
        [
          451.0,
          519.0
        ],
        [
          453.0,
          521.0
        ],
        [
          454.0,
          521.0
        ],
        [
          455.0,
          522.0
        ],
        [
          456.0,
          522.0
        ],
        [
          458.0,
          524.0
        ],
        [
          459.0,
          524.0
        ],
        [
          461.0,
          526.0
        ],
        [
          462.0,
          526.0
        ],
        [
          463.0,
          527.0
        ],
        [
          464.0,
          527.0
        ],
        [
          467.0,
          530.0
        ],
        [
          468.0,
          530.0
        ],
        [
          469.0,
          531.0
        ],
        [
          470.0,
          531.0
        ],
        [
          473.0,
          534.0
        ],
        [
          475.0,
          534.0
        ],
        [
          476.0,
          535.0
        ],
        [
          478.0,
          535.0
        ],
        [
          479.0,
          536.0
        ],
        [
          483.0,
          536.0
        ],
        [
          486.0,
          539.0
        ],
        [
          486.0,
          540.0
        ],
        [
          487.0,
          541.0
        ],
        [
          488.0,
          541.0
        ],
        [
          489.0,
          542.0
        ],
        [
          494.0,
          542.0
        ],
        [
          495.0,
          543.0
        ],
        [
          497.0,
          543.0
        ],
        [
          498.0,
          544.0
        ],
        [
          500.0,
          544.0
        ],
        [
          501.0,
          545.0
        ],
        [
          502.0,
          545.0
        ],
        [
          507.0,
          550.0
        ],
        [
          511.0,
          550.0
        ],
        [
          515.0,
          546.0
        ],
        [
          515.0,
          545.0
        ],
        [
          516.0,
          544.0
        ],
        [
          517.0,
          544.0
        ],
        [
          519.0,
          542.0
        ],
        [
          519.0,
          541.0
        ],
        [
          520.0,
          540.0
        ],
        [
          520.0,
          534.0
        ],
        [
          519.0,
          534.0
        ],
        [
          513.0,
          528.0
        ],
        [
          513.0,
          526.0
        ],
        [
          512.0,
          525.0
        ],
        [
          512.0,
          522.0
        ],
        [
          513.0,
          521.0
        ],
        [
          513.0,
          518.0
        ],
        [
          515.0,
          516.0
        ],
        [
          515.0,
          515.0
        ],
        [
          518.0,
          512.0
        ],
        [
          518.0,
          511.0
        ],
        [
          522.0,
          507.0
        ],
        [
          522.0,
          506.0
        ],
        [
          523.0,
          505.0
        ],
        [
          523.0,
          504.0
        ],
        [
          524.0,
          503.0
        ],
        [
          524.0,
          502.0
        ],
        [
          526.0,
          500.0
        ],
        [
          527.0,
          500.0
        ],
        [
          530.0,
          497.0
        ],
        [
          530.0,
          496.0
        ],
        [
          531.0,
          495.0
        ],
        [
          531.0,
          494.0
        ],
        [
          533.0,
          492.0
        ],
        [
          533.0,
          491.0
        ],
        [
          534.0,
          490.0
        ],
        [
          534.0,
          489.0
        ],
        [
          536.0,
          487.0
        ],
        [
          536.0,
          486.0
        ],
        [
          538.0,
          484.0
        ],
        [
          538.0,
          481.0
        ],
        [
          539.0,
          480.0
        ],
        [
          539.0,
          479.0
        ],
        [
          538.0,
          478.0
        ],
        [
          538.0,
          477.0
        ],
        [
          536.0,
          475.0
        ],
        [
          536.0,
          474.0
        ],
        [
          534.0,
          472.0
        ],
        [
          533.0,
          472.0
        ],
        [
          529.0,
          468.0
        ],
        [
          528.0,
          468.0
        ],
        [
          525.0,
          465.0
        ],
        [
          524.0,
          465.0
        ],
        [
          522.0,
          463.0
        ],
        [
          521.0,
          463.0
        ],
        [
          519.0,
          461.0
        ],
        [
          518.0,
          461.0
        ],
        [
          517.0,
          460.0
        ],
        [
          516.0,
          460.0
        ],
        [
          511.0,
          455.0
        ],
        [
          510.0,
          455.0
        ],
        [
          508.0,
          453.0
        ],
        [
          507.0,
          453.0
        ],
        [
          506.0,
          452.0
        ],
        [
          504.0,
          452.0
        ],
        [
          503.0,
          451.0
        ],
        [
          502.0,
          451.0
        ],
        [
          501.0,
          450.0
        ],
        [
          500.0,
          450.0
        ],
        [
          495.0,
          445.0
        ],
        [
          494.0,
          445.0
        ],
        [
          492.0,
          443.0
        ],
        [
          491.0,
          443.0
        ],
        [
          489.0,
          441.0
        ],
        [
          488.0,
          441.0
        ],
        [
          487.0,
          440.0
        ],
        [
          486.0,
          440.0
        ],
        [
          484.0,
          438.0
        ],
        [
          483.0,
          438.0
        ],
        [
          481.0,
          436.0
        ],
        [
          480.0,
          436.0
        ],
        [
          479.0,
          435.0
        ],
        [
          478.0,
          435.0
        ],
        [
          477.0,
          434.0
        ],
        [
          476.0,
          434.0
        ],
        [
          474.0,
          432.0
        ],
        [
          473.0,
          432.0
        ],
        [
          472.0,
          431.0
        ],
        [
          471.0,
          431.0
        ],
        [
          470.0,
          430.0
        ],
        [
          469.0,
          430.0
        ],
        [
          467.0,
          428.0
        ],
        [
          466.0,
          428.0
        ],
        [
          464.0,
          426.0
        ],
        [
          463.0,
          426.0
        ],
        [
          461.0,
          424.0
        ],
        [
          460.0,
          424.0
        ],
        [
          459.0,
          423.0
        ],
        [
          458.0,
          423.0
        ],
        [
          456.0,
          421.0
        ],
        [
          455.0,
          421.0
        ],
        [
          453.0,
          419.0
        ],
        [
          452.0,
          419.0
        ],
        [
          451.0,
          418.0
        ],
        [
          450.0,
          418.0
        ],
        [
          447.0,
          415.0
        ],
        [
          446.0,
          415.0
        ],
        [
          444.0,
          413.0
        ],
        [
          443.0,
          413.0
        ],
        [
          441.0,
          411.0
        ],
        [
          440.0,
          411.0
        ],
        [
          439.0,
          410.0
        ],
        [
          438.0,
          410.0
        ],
        [
          437.0,
          409.0
        ],
        [
          436.0,
          409.0
        ],
        [
          435.0,
          408.0
        ],
        [
          434.0,
          408.0
        ],
        [
          433.0,
          407.0
        ],
        [
          430.0,
          407.0
        ],
        [
          429.0,
          406.0
        ]
      ],
      "group_id": null,
      "description": "",
      "shape_type": "polygon",
      "flags": {}
    },
    {
      "label": "battery",
      "points": [
        [
          439.4904458598726,
          423.5668789808917
        ],
        [
          424.84076433121015,
          446.1783439490446
        ],
        [
          512.420382165605,
          502.2292993630573
        ],
        [
          520.7006369426751,
          494.9044585987261
        ],
        [
          527.3885350318471,
          479.61783439490443
        ],
        [
          523.5668789808917,
          476.4331210191083
        ],
        [
          443.9490445859872,
          423.2484076433121
        ]
      ],
      "group_id": null,
      "description": "",
      "shape_type": "polygon",
      "flags": {}
    },
    {
      "label": "battery",
      "points": [
        [
          421.0191082802548,
          451.9108280254777
        ],
        [
          412.4203821656051,
          460.50955414012736
        ],
        [
          405.09554140127386,
          474.5222929936306
        ],
        [
          494.5859872611465,
          531.8471337579617
        ],
        [
          501.27388535031844,
          524.5222929936306
        ],
        [
          506.68789808917194,
          514.3312101910827
        ],
        [
          507.3248407643312,
          506.0509554140127
        ]
      ],
      "group_id": null,
      "description": "",
      "shape_type": "polygon",
      "flags": {}
    }
  ],
  "imagePath": "4.jpg",
  "imageData": null,
  "imageHeight": 1450,
  "imageWidth": 1450
}