{
  "version": "5.2.0.post4",
  "flags": {},
  "shapes": [
    {
      "label": "hca_back",
      "points": [
        [
          864.5064935064935,
          744.6493506493506
        ],
        [
          761.9090909090909,
          853.7402597402597
        ],
        [
          696.974025974026,
          922.5714285714286
        ],
        [
          693.077922077922,
          938.1558441558441
        ],
        [
          709.961038961039,
          962.8311688311688
        ],
        [
          748.922077922078,
          994.0
        ],
        [
          751.5194805194805,
          994.0
        ],
        [
          932.038961038961,
          799.1948051948052
        ],
        [
          917.7532467532467,
          773.2207792207791
        ],
        [
          890.4805194805194,
          751.1428571428571
        ]
      ],
      "group_id": null,
      "description": null,
      "shape_type": "polygon",
      "flags": {}
    },
    {
      "label": "battery",
      "points": [
        [
          872.2987012987013,
          765.4285714285714
        ],
        [
          859.3116883116883,
          782.3116883116883
        ],
        [
          891.7792207792207,
          813.4805194805194
        ],
        [
          909.961038961039,
          795.2987012987013
        ]
      ],
      "group_id": null,
      "description": null,
      "shape_type": "polygon",
      "flags": {}
    },
    {
      "label": "internals",
      "points": [
        [
          837.8378378378378,
          782.1621621621621
        ],
        [
          737.2972972972973,
          893.5135135135134
        ],
        [
          751.3513513513514,
          895.6756756756756
        ],
        [
          757.2972972972973,
          902.1621621621621
        ],
        [
          761.6216216216216,
          909.7297297297297
        ],
        [
          770.8108108108107,
          921.6216216216216
        ],
        [
          777.8378378378378,
          925.4054054054054
        ],
        [
          785.4054054054054,
          927.027027027027
        ],
        [
          789.7297297297297,
          932.4324324324324
        ],
        [
          791.3513513513514,
          941.081081081081
        ],
        [
          895.6756756756756,
          834.0540540540541
        ],
        [
          885.9459459459459,
          824.8648648648648
        ],
        [
          894.5945945945946,
          815.1351351351351
        ],
        [
          856.2162162162161,
          780.0
        ],
        [
          848.108108108108,
          788.6486486486486
        ]
      ],
      "group_id": null,
      "description": null,
      "shape_type": "polygon",
      "flags": {}
    },
    {
      "label": "gap",
      "points": [
        [
          737.2596153846154,
          896.875
        ],
        [
          703.3653846153846,
          931.7307692307692
        ],
        [
          707.4519230769231,
          941.8269230769231
        ],
        [
          718.9903846153846,
          956.25
        ],
        [
          731.7307692307692,
          967.5480769230769
        ],
        [
          744.4711538461538,
          979.0865384615385
        ],
        [
          752.4038461538461,
          984.6153846153845
        ],
        [
          789.4230769230769,
          942.3076923076923
        ],
        [
          789.4230769230769,
          934.1346153846154
        ],
        [
          782.4519230769231,
          928.6057692307692
        ],
        [
          773.3173076923076,
          927.4038461538461
        ],
        [
          764.9038461538461,
          919.2307692307692
        ],
        [
          759.6153846153846,
          909.8557692307692
        ],
        [
          756.25,
          903.3653846153845
        ],
        [
          751.9230769230769,
          899.0384615384615
        ],
        [
          744.2307692307692,
          897.5961538461538
        ]
      ],
      "group_id": null,
      "description": "",
      "shape_type": "polygon",
      "flags": {}
    }
  ],
  "imagePath": "2.png",
  "imageData": null,
  "imageHeight": 1450,
  "imageWidth": 1450,
  "module": "vision",
  "camera": "basler"
}